ChangeLog
LICENSE
setup.cfg
setup.py
src/protobuf/__init__.py
src/protobuf.socketrpc.egg-info/PKG-INFO
src/protobuf.socketrpc.egg-info/SOURCES.txt
src/protobuf.socketrpc.egg-info/dependency_links.txt
src/protobuf.socketrpc.egg-info/top_level.txt
src/protobuf/socketrpc/__init__.py
src/protobuf/socketrpc/channel.py
src/protobuf/socketrpc/controller.py
src/protobuf/socketrpc/error.py
src/protobuf/socketrpc/logger.py
src/protobuf/socketrpc/rpc.proto
src/protobuf/socketrpc/rpc_pb2.py
src/protobuf/socketrpc/server.py
src/protobuf/socketrpc/service.py
src/protobuf/socketrpc/examples/__init__.py
src/protobuf/socketrpc/examples/helloworld/HelloWorldServiceImpl.py
src/protobuf/socketrpc/examples/helloworld/__init__.py
src/protobuf/socketrpc/examples/helloworld/hello_world.proto
src/protobuf/socketrpc/examples/helloworld/hello_world_pb2.py
src/protobuf/socketrpc/examples/helloworld/run_client.py
src/protobuf/socketrpc/examples/helloworld/run_server.py
src/protobuf/socketrpc/examples/time/__init__.py
src/protobuf/socketrpc/examples/time/run_client.py
src/protobuf/socketrpc/examples/time/run_server.py
src/protobuf/socketrpc/examples/time/time.proto
src/protobuf/socketrpc/examples/time/time_pb2.py
src/protobuf/socketrpc/tests/__init__.py
src/protobuf/socketrpc/tests/channel_test.py
src/protobuf/socketrpc/tests/controller_test.py
src/protobuf/socketrpc/tests/error_test.py
src/protobuf/socketrpc/tests/fake.py
src/protobuf/socketrpc/tests/run_tests.py
src/protobuf/socketrpc/tests/server_test.py
src/protobuf/socketrpc/tests/service_test.py
src/protobuf/socketrpc/tests/test.proto
src/protobuf/socketrpc/tests/test_pb2.py