Metadata-Version: 1.1
Name: protobuf.socketrpc
Version: 1.3.2
Summary: a Python implementation of protobuf RPC over sockets
Home-page: http://code.google.com/p/protobuf-socket-rpc/
Author: Shardul Deo
Author-email: shardul.deo@gmail.com
License: UNKNOWN
Platform: UNKNOWN
Classifier: Intended Audience :: Developers
Classifier: License :: OSI Approved :: MIT License
Classifier: Operating System :: OS Independent
Classifier: Programming Language :: Python
Classifier: Topic :: Software Development :: Libraries :: Python Modules
